topsis/__init__.py
topsis/__main__.py
Topsis_Lakshit_102017054-1.0.5.dist-info/LICENSE
Topsis_Lakshit_102017054-1.0.5.dist-info/METADATA
Topsis_Lakshit_102017054-1.0.5.dist-info/WHEEL
Topsis_Lakshit_102017054-1.0.5.dist-info/entry_points.txt
Topsis_Lakshit_102017054-1.0.5.dist-info/top_level.txt
Topsis_Lakshit_102017054-1.0.5.dist-info/RECORD
