Metadata-Version: 2.1
Name: Topsis-Lakshit-102017054
Version: 1.0.5
Summary: topsis implementation
Home-page: 
Author: Lakshit Patidar
Author-email: lpatidar_be20@thapar.edu
Classifier: Programming Language :: Python :: 3
Classifier: License :: OSI Approved :: MIT License
Classifier: Operating System :: OS Independent
Requires-Python: >=3.6
License-File: LICENSE
